<!DOCTYPE HTML PUBLIC "-//W3C//DTD HTML 4.01 Transitional//EN">
<HTML lang="ja">
<HEAD>
<TITLE>2006/01/06 ï¿½ï¿½ï¿½L: Apache Jakarta BCELï¿½ï¿½pï¿½ï¿½ï¿½ï¿½ï¿½Nï¿½ï¿½ï¿½Xï¿½tï¿½@ï¿½Cï¿½ï¿½(ï¿½oï¿½Cï¿½gï¿½Rï¿½[ï¿½h)ï¿½ï¿½ÍƒTï¿½ï¿½ï¿½vï¿½ï¿½</TITLE>
<META name="DESCRIPTION" content="blancoDb Enterprise Edition 1.4.0, blancoResourceBundle 0.4.5, BlancoSqlEditorPlugin 0.3.4ï¿½É‚Â‚ï¿½ï¿½ÄAï¿½oï¿½×Œï¿½ï¿½Å‚ï¿½ï¿½ï¿½ï¿½ï¿½ï¿½[ï¿½Xï¿½ï¿½ï¿½Ü‚ï¿½ï¿½B">
<META name="KEYWORDS" content="ï¿½ï¿½ï¿½ï¿½ï¿½Ò‚ï¿½ï¿½Ì“ï¿½ï¿½Lv2,diary,igapyon,Apache,BCEL,ï¿½oï¿½Cï¿½gï¿½Rï¿½[ï¿½h">
<META name="GENERATOR" content="IBM WebSphere Studio Homepage Builder Version 11.0.3.0 for Windows">
<META name="DATE" content="2010-09-27T20:42:49+09:00">
<META http-equiv="Content-Type" content="text/html; charset=Shift_JIS">
<META http-equiv="Content-Style-Type" content="text/css">
<LINK rel="INDEX" href="index.html">
<LINK rel="CONTENTS" href="index.html">
<LINK rel="stylesheet" href="../../css/table.css" type="text/css" id="_HPB_TABLE_CSS_ID_">
</HEAD>
<BODY bgcolor="#eeddcc">
<TABLE border="0"><TBODY><TR>
  <TD valign="top">
    <A href="../memo/memoigapyon.html">
      <IMG src="../../image/iga200306s.jpg" border="0" ALT="ï¿½ï¿½ï¿½ï¿½ï¿½Ò‚ï¿½ï¿½æ‘œ(ï¿½ï¿½) 2003/06">
    </A>
  </TD>
  <TD valign="top">
    <H2>2006/01/06 ï¿½ï¿½ï¿½L: Apache Jakarta BCELï¿½ï¿½pï¿½ï¿½ï¿½ï¿½ï¿½Nï¿½ï¿½ï¿½Xï¿½tï¿½@ï¿½Cï¿½ï¿½(ï¿½oï¿½Cï¿½gï¿½Rï¿½[ï¿½h)ï¿½ï¿½ÍƒTï¿½ï¿½ï¿½vï¿½ï¿½</H2>
    <P>[ï¿½ï¿½ï¿½ï¿½ï¿½Ò‚ï¿½ï¿½Ì“ï¿½ï¿½Lv2,diary,igapyon,Apache,BCEL,ï¿½oï¿½Cï¿½gï¿½Rï¿½[ï¿½h] blancoDb Enterprise Edition 1.4.0, blancoResourceBundle 0.4.5, BlancoSqlEditorPlugin 0.3.4ï¿½É‚Â‚ï¿½ï¿½ÄAï¿½oï¿½×Œï¿½ï¿½Å‚ï¿½ï¿½ï¿½ï¿½ï¿½ï¿½[ï¿½Xï¿½ï¿½ï¿½Ü‚ï¿½ï¿½B</P>
  </TD>
</TR></TBODY></TABLE>

<!-- adv -->
<CENTER>
<TABLE bgcolor="#ffff00" summary="adv">
  <TBODY>
    <TR>

      <TD align="center">ï¿½Lï¿½ï¿½: <A href="http://journal.mycom.co.jp/column/ide/091/">ï¿½Cï¿½}ï¿½hï¿½Lï¿½ï¿½IDEï¿½ï¿½ï¿½ï¿½: Eclipseï¿½xï¿½[ï¿½Xï¿½Ì“ï¿½ï¿½ï¿½ï¿½|ï¿½ï¿½Â‹ï¿½ï¿½uBentenï¿½vï¿½ï¿½ï¿½gï¿½ï¿½ï¿½Ä‚İ‚æ‚¤</A> <FONT color="#ff0000" size="-1">09/27</FONT><BR>
        <FONT size="-1">ï¿½ï¿½ï¿½ï¿½ï¿½ï¿½ï¿½ï¿½ï¿½ï¿½ï¿½ï¿½Ìï¿½É‚ï¿½ï¿½ Benten ï¿½Ğ‰ï¿½Lï¿½ï¿½!</FONT></TD>

    </TR>
  </TBODY>
</TABLE>
</CENTER>
<!-- adv -->




<P> </P>

<DIV align="right">
<TABLE cellpadding="4">
  <TBODY>
    <TR bgcolor="#99ccff">
      <TD><A href="../idxall.html">ï¿½Cï¿½ï¿½ï¿½fï¿½Bï¿½bï¿½Nï¿½Xï¿½yï¿½[ï¿½Wï¿½Ö–ß‚ï¿½</A></TD>
    </TR>
  </TBODY>
</TABLE>
</DIV>



<TABLE summary="mini title">
  <TBODY>
    <TR>
      <TD bgcolor="#ff9900" valign="top"><FONT color="#ffffff" size="+1"><STRONG>Apache Jakarta BCELï¿½ï¿½pï¿½ï¿½ï¿½ï¿½ï¿½Nï¿½ï¿½ï¿½Xï¿½tï¿½@ï¿½Cï¿½ï¿½(ï¿½oï¿½Cï¿½gï¿½Rï¿½[ï¿½h)ï¿½ï¿½ÍƒTï¿½ï¿½ï¿½vï¿½ï¿½</STRONG></FONT></TD>
    </TR>
  </TBODY>
</TABLE>
<P>ï¿½sï¿½Ó‚ï¿½30ï¿½ï¿½ï¿½Ù‚Çï¿½ï¿½Ô‚ï¿½ï¿½ï¿½ï¿½Rï¿½É‚È‚ï¿½ï¿½ï¿½ï¿½Ì‚ÅAApache Jakarta BCELï¿½ï¿½pï¿½ï¿½ï¿½ï¿½ï¿½Nï¿½ï¿½ï¿½Xï¿½tï¿½@ï¿½Cï¿½ï¿½ï¿½ï¿½ï¿½(ï¿½oï¿½Cï¿½gï¿½Rï¿½[ï¿½hï¿½ï¿½ï¿½)ï¿½ï¿½ï¿½ï¿½ï¿½ï¿½ï¿½Ä‚İ‚Ü‚ï¿½ï¿½ï¿½ï¿½Bï¿½Æ‚Ä‚ï¿½ï¿½È’Pï¿½É“ï¿½ï¿½ì‚³ï¿½ï¿½ï¿½é‚±ï¿½Æ‚ï¿½ï¿½oï¿½ï¿½ï¿½Ü‚ï¿½ï¿½ï¿½ï¿½B</P>
<UL>
  <LI>Apache Jakarta BCEL 5.1<BR>
  <A HREF="http://jakarta.apache.org/bcel/index.html">http://jakarta.apache.org/bcel/index.html</A>
  <LI>Sun JDK 1.4.2_10 (Windowsï¿½ï¿½)
</UL>
<BLOCKQUOTE>
<TABLE border="1">
  <TBODY>
    <TR>
      <TD bgcolor="#ffff00">BcelReadClassSample.java</TD>
    </TR>
  </TBODY>
</TABLE>
<TABLE border="1">
  <TBODY>
    <TR>
      <TD>
      <pre>/**
 * Apache Jakarta BCELï¿½ï¿½pï¿½ï¿½ï¿½ï¿½ï¿½Nï¿½ï¿½ï¿½Xï¿½tï¿½@ï¿½Cï¿½ï¿½(ï¿½oï¿½Cï¿½gï¿½Rï¿½[ï¿½h)ï¿½ï¿½ÍƒTï¿½ï¿½ï¿½vï¿½ï¿½
 */
import java.io.IOException;

import org.apache.bcel.classfile.ClassFormatException;
import org.apache.bcel.classfile.ClassParser;
import org.apache.bcel.classfile.Code;
import org.apache.bcel.classfile.JavaClass;
import org.apache.bcel.classfile.Method;
import org.apache.bcel.classfile.Utility;

/**
 * Apache Jakarta BCELï¿½ï¿½pï¿½ï¿½ï¿½ï¿½ï¿½Nï¿½ï¿½ï¿½Xï¿½tï¿½@ï¿½Cï¿½ï¿½(ï¿½oï¿½Cï¿½gï¿½Rï¿½[ï¿½h)ï¿½ï¿½ÍƒTï¿½ï¿½ï¿½vï¿½ï¿½
 * 
 * @author IGA Tosiki
 */
public class BcelReadClassSample {
    /**
     * ï¿½ï¿½Í‚ï¿½ï¿½sï¿½ï¿½ï¿½ï¿½ï¿½ï¿½ï¿½Nï¿½ï¿½ï¿½Xï¿½tï¿½@ï¿½Cï¿½ï¿½ï¿½ï¿½ï¿½ï¿½ï¿½wï¿½è‚µï¿½Ü‚ï¿½ï¿½B
     */
    private static final String CLASS_MODULE = &quot;./bin/BcelReadClassSample.class&quot;;

    public static final void main(final String[] args) {
        new BcelReadClassSample().process();
    }

    private final void process() {
        try {
            final JavaClass javaClass = new ClassParser(CLASS_MODULE).parse();
            System.out.println(&quot;ï¿½Nï¿½ï¿½ï¿½Xï¿½ï¿½:&quot; + javaClass.getClassName());
            System.out.println(&quot;ï¿½eï¿½Nï¿½ï¿½ï¿½X:&quot; + javaClass.getSuperclassName());

            final org.apache.bcel.classfile.Method[] methods = javaClass
                    .getMethods();
            for (int indexMethod = 0; indexMethod &lt; methods.length; indexMethod++) {
                final Method method = methods[indexMethod];
                System.out.println(&quot;ï¿½ï¿½ï¿½\ï¿½bï¿½h:&quot; + method.getName());
                final Code code = method.getCode();
                if (code == null) {
                    continue;
                }

                /**
                 * ï¿½ï¿½ï¿½\ï¿½bï¿½hï¿½Ì‚È‚ï¿½ï¿½Ìƒoï¿½Cï¿½gï¿½Rï¿½[ï¿½hï¿½ï¿½ï¿½ï¿½ï¿½
                 */
                final String result = Utility.codeToString(code.getCode(),
                        javaClass.getConstantPool(), 0, -1, false);
                System.out.println(result);
            }
        } catch (ClassFormatException e) {
            e.printStackTrace();
        } catch (IOException e) {
            e.printStackTrace();
        }
    }
}</pre>
      </TD>
    </TR>
  </TBODY>
</TABLE>
</BLOCKQUOTE>
<P>ï¿½ï¿½ï¿½sï¿½ï¿½ï¿½Ê‚Í‰ï¿½ï¿½Lï¿½Ì‚æ‚¤ï¿½É‚È‚ï¿½Ü‚ï¿½ï¿½Bï¿½å—§ï¿½ï¿½ï¿½ï¿½ï¿½ï¿½ï¿½ï¿½ï¿½ï¿½ Utility.codeToString ï¿½Ì‚È‚ï¿½ï¿½Åsï¿½ï¿½ï¿½Ä‚ï¿½ï¿½Ü‚ï¿½ï¿½B</P>
<BLOCKQUOTE>
<TABLE border="1">
  <TBODY>
    <TR>
      <TD bgcolor="#ffff00">ï¿½ï¿½ï¿½sï¿½ï¿½ï¿½ï¿½</TD>
    </TR>
  </TBODY>
</TABLE>
<TABLE border="1">
  <TBODY>
    <TR>
      <TD>
      <pre>ï¿½Nï¿½ï¿½ï¿½Xï¿½ï¿½:BcelReadClassSample
ï¿½eï¿½Nï¿½ï¿½ï¿½X:java.lang.Object
ï¿½ï¿½ï¿½\ï¿½bï¿½h:&lt;init&gt;
0:    aload_0
1:    invokespecial     java.lang.Object.&lt;init&gt; ()V
4:    return

ï¿½ï¿½ï¿½\ï¿½bï¿½h:main
0:    new               &lt;BcelReadClassSample&gt;
3:    dup
4:    invokespecial     BcelReadClassSample.&lt;init&gt; ()V
7:    invokespecial     BcelReadClassSample.process ()V
10:   return

ï¿½ï¿½ï¿½\ï¿½bï¿½h:process
0:    new               &lt;org.apache.bcel.classfile.ClassParser&gt;
3:    dup
4:    ldc               &quot;./bin/BcelReadClassSample.class&quot;
6:    invokespecial     org.apache.bcel.classfile.ClassParser.&lt;init&gt; (Ljava/lang/String;)V
9:    invokevirtual     org.apache.bcel.classfile.ClassParser.parse ()Lorg/apache/bcel/classfile/JavaClass;
12:   astore_1
13:   getstatic         java.lang.System.out Ljava/io/PrintStream;
16:   new               &lt;java.lang.StringBuffer&gt;
19:   dup
20:   ldc               &quot;ï¿½Nï¿½ï¿½ï¿½Xï¿½ï¿½:&quot;
22:   invokespecial     java.lang.StringBuffer.&lt;init&gt; (Ljava/lang/String;)V
25:   aload_1
26:   invokevirtual     org.apache.bcel.classfile.JavaClass.getClassName ()Ljava/lang/String;
29:   invokevirtual     java.lang.StringBuffer.append (Ljava/lang/String;)Ljava/lang/StringBuffer;
32:   invokevirtual     java.lang.StringBuffer.toString ()Ljava/lang/String;
35:   invokevirtual     java.io.PrintStream.println (Ljava/lang/String;)V
38:   getstatic         java.lang.System.out Ljava/io/PrintStream;
41:   new               &lt;java.lang.StringBuffer&gt;
44:   dup
45:   ldc               &quot;ï¿½eï¿½Nï¿½ï¿½ï¿½X:&quot;
47:   invokespecial     java.lang.StringBuffer.&lt;init&gt; (Ljava/lang/String;)V
50:   aload_1
51:   invokevirtual     org.apache.bcel.classfile.JavaClass.getSuperclassName ()Ljava/lang/String;
54:   invokevirtual     java.lang.StringBuffer.append (Ljava/lang/String;)Ljava/lang/StringBuffer;
57:   invokevirtual     java.lang.StringBuffer.toString ()Ljava/lang/String;
60:   invokevirtual     java.io.PrintStream.println (Ljava/lang/String;)V
63:   aload_1
64:   invokevirtual     org.apache.bcel.classfile.JavaClass.getMethods ()[Lorg/apache/bcel/classfile/Method;
67:   astore_2
68:   iconst_0
69:   istore_3
70:   goto              #147
73:   aload_2
74:   iload_3
75:   aaload
76:   astore            %4
78:   getstatic         java.lang.System.out Ljava/io/PrintStream;
81:   new               &lt;java.lang.StringBuffer&gt;
84:   dup
85:   ldc               &quot;ï¿½ï¿½ï¿½\ï¿½bï¿½h:&quot;
87:   invokespecial     java.lang.StringBuffer.&lt;init&gt; (Ljava/lang/String;)V
90:   aload             %4
92:   invokevirtual     org.apache.bcel.classfile.Method.getName ()Ljava/lang/String;
95:   invokevirtual     java.lang.StringBuffer.append (Ljava/lang/String;)Ljava/lang/StringBuffer;
98:   invokevirtual     java.lang.StringBuffer.toString ()Ljava/lang/String;
101:  invokevirtual     java.io.PrintStream.println (Ljava/lang/String;)V
104:  aload             %4
106:  invokevirtual     org.apache.bcel.classfile.Method.getCode ()Lorg/apache/bcel/classfile/Code;
109:  astore            %5
111:  aload             %5
113:  ifnonnull         #119
116:  goto              #144
119:  aload             %5
121:  invokevirtual     org.apache.bcel.classfile.Code.getCode ()[B
124:  aload_1
125:  invokevirtual     org.apache.bcel.classfile.JavaClass.getConstantPool ()Lorg/apache/bcel/classfile/ConstantPool;
128:  iconst_0
129:  iconst_m1
130:  iconst_0
131:  invokestatic      org.apache.bcel.classfile.Utility.codeToString ([BLorg/apache/bcel/classfile/ConstantPool;IIZ)Ljava/lang/String;
134:  astore            %6
136:  getstatic         java.lang.System.out Ljava/io/PrintStream;
139:  aload             %6
141:  invokevirtual     java.io.PrintStream.println (Ljava/lang/String;)V
144:  iinc              %3      1
147:  iload_3
148:  aload_2
149:  arraylength
150:  if_icmplt         #73
153:  goto              #169
156:  astore_1
157:  aload_1
158:  invokevirtual     org.apache.bcel.classfile.ClassFormatException.printStackTrace ()V
161:  goto              #169
164:  astore_1
165:  aload_1
166:  invokevirtual     java.io.IOException.printStackTrace ()V
169:  return
</pre>
      </TD>
    </TR>
  </TBODY>
</TABLE>
</BLOCKQUOTE>
<HR>
<P>ï¿½ï¿½ï¿½Ì—á‚¾ï¿½ï¿½ ï¿½ï¿½ï¿½Ü‚ï¿½É‚ï¿½BCELï¿½ï¿½Utility.codeToStringï¿½ÉˆË‘ï¿½ï¿½ï¿½ï¿½ï¿½ï¿½ï¿½ï¿½Ä‚ï¿½ï¿½ï¿½Ì‚ÅAï¿½ï¿½ï¿½ï¿½ï¿½ï¿½ï¿½}ï¿½Wï¿½ï¿½ï¿½Éƒvï¿½ï¿½ï¿½Oï¿½ï¿½ï¿½ï¿½ï¿½Æ‚ï¿½ï¿½Ä‰ï¿½Í‚ï¿½ï¿½ï¿½ï¿½ï¿½ï¿½ï¿½ï¿½ï¿½ï¿½Ü‚ï¿½ï¿½B</P>
<BLOCKQUOTE>
<TABLE border="1">
  <TBODY>
    <TR>
      <TD bgcolor="#ffff00">BcelReadClassSample.java</TD>
    </TR>
  </TBODY>
</TABLE>
<TABLE border="1">
  <TBODY>
    <TR>
      <TD>
      <pre>/**
 * Apache Jakarta BCELï¿½ï¿½pï¿½ï¿½ï¿½ï¿½ï¿½Nï¿½ï¿½ï¿½Xï¿½tï¿½@ï¿½Cï¿½ï¿½(ï¿½oï¿½Cï¿½gï¿½Rï¿½[ï¿½h)ï¿½ï¿½ÍƒTï¿½ï¿½ï¿½vï¿½ï¿½
 */
import java.io.IOException;

import org.apache.bcel.Constants;
import org.apache.bcel.classfile.ClassFormatException;
import org.apache.bcel.classfile.ClassParser;
import org.apache.bcel.classfile.Code;
import org.apache.bcel.classfile.JavaClass;
import org.apache.bcel.classfile.Method;

/**
 * Apache Jakarta BCELï¿½ï¿½pï¿½ï¿½ï¿½ï¿½ï¿½Nï¿½ï¿½ï¿½Xï¿½tï¿½@ï¿½Cï¿½ï¿½(ï¿½oï¿½Cï¿½gï¿½Rï¿½[ï¿½h)ï¿½ï¿½ÍƒTï¿½ï¿½ï¿½vï¿½ï¿½ï¿½B
 * 
 * ï¿½ï¿½ï¿½ï¿½ï¿½}ï¿½Wï¿½ï¿½ï¿½É‰ï¿½Í‚ï¿½ï¿½ï¿½ï¿½
 * 
 * @author IGA Tosiki
 */
public class BcelReadClassSample {
    /**
     * ï¿½ï¿½Í‚ï¿½ï¿½sï¿½ï¿½ï¿½ï¿½ï¿½ï¿½ï¿½Nï¿½ï¿½ï¿½Xï¿½tï¿½@ï¿½Cï¿½ï¿½ï¿½ï¿½ï¿½ï¿½ï¿½wï¿½è‚µï¿½Ü‚ï¿½ï¿½B
     */
    private static final String CLASS_MODULE = &quot;./bin/BcelReadClassSample.class&quot;;

    public static final void main(final String[] args) {
        new BcelReadClassSample().process();
    }

    private final void process() {
        try {
            final JavaClass javaClass = new ClassParser(CLASS_MODULE).parse();
            System.out.println(&quot;ï¿½Nï¿½ï¿½ï¿½Xï¿½ï¿½:&quot; + javaClass.getClassName());
            System.out.println(&quot;ï¿½eï¿½Nï¿½ï¿½ï¿½X:&quot; + javaClass.getSuperclassName());

            final org.apache.bcel.classfile.Method[] methods = javaClass
                    .getMethods();
            for (int indexMethod = 0; indexMethod &lt; methods.length; indexMethod++) {
                final Method method = methods[indexMethod];
                System.out.println(&quot;ï¿½ï¿½ï¿½\ï¿½bï¿½h:&quot; + method.getName());
                final Code code = method.getCode();
                if (code == null) {
                    continue;
                }

                /**
                 * ï¿½ï¿½ï¿½\ï¿½bï¿½hï¿½Ì‚È‚ï¿½ï¿½Ìƒoï¿½Cï¿½gï¿½Rï¿½[ï¿½hï¿½ï¿½ï¿½ï¿½ï¿½
                 */
                final byte[] codes = code.getCode();
                for (int indexCode = 0; indexCode &lt; codes.length; indexCode++) {
                    final short opcode = (short) (codes[indexCode] &lt; 0 ? ((short) codes[indexCode]) + 0x100
                            : (short) codes[indexCode]);
                    int oplen = Constants.NO_OF_OPERANDS[opcode];
                    System.out.println(Constants.OPCODE_NAMES[opcode]);

                    // ï¿½Iï¿½yï¿½ï¿½ï¿½[ï¿½Vï¿½ï¿½ï¿½ï¿½ï¿½ï¿½ï¿½iï¿½ß‚Ü‚ï¿½ï¿½B
                    indexCode += oplen;
                }
            }
        } catch (ClassFormatException e) {
            e.printStackTrace();
        } catch (IOException e) {
            e.printStackTrace();
        }
    }
}
</pre>
      </TD>
    </TR>
  </TBODY>
</TABLE>
</BLOCKQUOTE>
<P>ï¿½ï¿½ï¿½ß•ï¿½ï¿½Ì•\ï¿½ï¿½ï¿½ï¿½ï¿½ï¿½ï¿½ï¿½ï¿½Ä‚ï¿½ï¿½È‚ï¿½ï¿½Ì‚ÅAï¿½ï¿½ï¿½sï¿½ï¿½ÌŒï¿½ï¿½Ê‚Íï¿½ï¿½È‚ï¿½ï¿½È‚ï¿½ï¿½Ä‚ï¿½ï¿½Ü‚ï¿½ï¿½Ü‚ï¿½ï¿½B</P>
<BLOCKQUOTE>
<TABLE border="1">
  <TBODY>
    <TR>
      <TD bgcolor="#ffff00">ï¿½ï¿½ï¿½sï¿½ï¿½ï¿½ï¿½</TD>
    </TR>
  </TBODY>
</TABLE>
<TABLE border="1">
  <TBODY>
    <TR>
      <TD>
      <pre>ï¿½Nï¿½ï¿½ï¿½Xï¿½ï¿½:BcelReadClassSample
ï¿½eï¿½Nï¿½ï¿½ï¿½X:java.lang.Object
ï¿½ï¿½ï¿½\ï¿½bï¿½h:&lt;init&gt;
aload_0
invokespecial
return
ï¿½ï¿½ï¿½\ï¿½bï¿½h:main
new
dup
invokespecial
invokespecial
return
ï¿½ï¿½ï¿½\ï¿½bï¿½h:process
new
dup
ldc
invokespecial
invokevirtual
astore_1
getstatic
new
dup
ldc
invokespecial
aload_1
invokevirtual
invokevirtual
invokevirtual
invokevirtual
getstatic
new
dup
ldc
invokespecial
aload_1
invokevirtual
invokevirtual
invokevirtual
invokevirtual
aload_1
invokevirtual
astore_2
iconst_0
istore_3
goto
aload_2
iload_3
aaload
astore
getstatic
new
dup
ldc
invokespecial
aload
invokevirtual
invokevirtual
invokevirtual
invokevirtual
aload
invokevirtual
astore
aload
ifnonnull
goto
aload
invokevirtual
astore
iconst_0
istore
goto
aload
iload
baload
ifge
aload
iload
baload
i2s
sipush
iadd
goto
aload
iload
baload
i2s
i2s
istore
getstatic
iload
saload
istore
getstatic
getstatic
iload
aaload
invokevirtual
iload
iload
iadd
istore
iinc
iload
aload
arraylength
if_icmplt
iinc
iload_3
aload_2
arraylength
if_icmplt
goto
astore_1
aload_1
invokevirtual
goto
astore_1
aload_1
invokevirtual
return
</pre>
      </TD>
    </TR>
  </TBODY>
</TABLE>
</BLOCKQUOTE>
<P>ï¿½ï¿½ï¿½\ BCELï¿½Ì•~ï¿½ï¿½ï¿½ï¿½ï¿½á‚¢ï¿½ï¿½ï¿½Æ‚ï¿½ï¿½í‚©ï¿½ï¿½Ü‚ï¿½ï¿½ï¿½ï¿½Bï¿½È‚ñ‚¾‚ï¿½ï¿½á…ï¿½ï¿½ï¿½ÉGï¿½ï¿½é‚±ï¿½Æ‚ï¿½ï¿½oï¿½ï¿½ï¿½ï¿½ ï¿½ï¿½ï¿½ï¿½ï¿½ï¿½ï¿½ï¿½ï¿½ï¿½ï¿½Å‚ï¿½ï¿½B</P>
<P>ï¿½ï¿½ï¿½ï¿½ï¿½ï¿½ï¿½ï¿½ï¿½ÎAï¿½ï¿½ï¿½É‚Æ‚ï¿½ï¿½ï¿½ BCELï¿½ÌÅ‚ï¿½ï¿½gï¿½ß‚È—ï¿½ï¿½pï¿½ï¿½ï¿½ FindBugsï¿½Å‚ï¿½ï¿½BFindBugsï¿½Íƒoï¿½Cï¿½gï¿½Rï¿½[ï¿½hï¿½ï¿½Í‚ï¿½ BCELï¿½ğ—˜—pï¿½ï¿½ï¿½Ä‚ï¿½ï¿½é‚±ï¿½Æ‚ï¿½ï¿½mï¿½ï¿½ï¿½Ä‚ï¿½ï¿½Ü‚ï¿½ï¿½B</P>
<P><FONT color="#ff0000">ï¿½ï¿½ï¿½ï¿½:</FONT> ï¿½ï¿½ï¿½Ìƒvï¿½ï¿½ï¿½Oï¿½ï¿½ï¿½ï¿½ï¿½ï¿½ï¿½ï¿½ï¿½sï¿½ï¿½ï¿½ï¿½ï¿½ ï¿½oï¿½Cï¿½gï¿½Rï¿½[ï¿½hï¿½ï¿½ï¿½Âï¿½ï¿½ï¿½ï¿½ï¿½ï¿½ï¿½Ü‚ï¿½ï¿½Bï¿½ï¿½ï¿½ï¿½ï¿½ï¿½ï¿½ï¿½Ìï¿½ï¿½ï¿½É‚ï¿½èƒŠï¿½oï¿½[ï¿½Xï¿½Gï¿½ï¿½ï¿½Wï¿½jï¿½Aï¿½ï¿½ï¿½ï¿½ï¿½Oï¿½ï¿½ï¿½Ö~ï¿½ï¿½ï¿½ï¿½Ä‚ï¿½ï¿½ï¿½Nï¿½ï¿½ï¿½Xï¿½tï¿½@ï¿½Cï¿½ï¿½ï¿½Í‰ï¿½Í‚ï¿½ï¿½×‚ï¿½ï¿½Å‚È‚ï¿½ï¿½Ælï¿½ï¿½ï¿½Ü‚ï¿½ï¿½B</P>
<P><FONT color="#ff0000">2006.01.10ï¿½Ç‹L</FONT> FindBugsï¿½Ìƒ\ï¿½[ï¿½Xï¿½Rï¿½[ï¿½hï¿½ï¿½ BCELï¿½Ì—ï¿½ï¿½pï¿½ï¿½Æ‚ï¿½ï¿½Ä‚Æ‚Ä‚ï¿½ï¿½Qï¿½lï¿½É‚È‚ï¿½Ü‚ï¿½ï¿½ï¿½ï¿½BBCELï¿½ï¿½ï¿½Ú‚ï¿½ï¿½ï¿½ï¿½mï¿½è‚½ï¿½ï¿½ï¿½ï¿½ï¿½É‚ï¿½ FindBugsï¿½Ìƒ\ï¿½[ï¿½Xï¿½Rï¿½[ï¿½hï¿½ï¿½Ç‚Ü‚ï¿½é‚±ï¿½Æ‚ï¿½ï¿½ï¿½ï¿½ï¿½ï¿½ß‚ï¿½ï¿½ï¿½ï¿½ï¿½ï¿½Ævï¿½ï¿½ï¿½Ü‚ï¿½ï¿½ï¿½ï¿½B</P>
<P><FONT color="#ff00ff">ï¿½Ö˜Aï¿½ï¿½ï¿½ï¿½\ï¿½[ï¿½X</FONT></P>
<UL>
  <LI>blancoBcel<BR>
  <A HREF="https://www.igapyon.jp/blanco/blancodownload.html#blancoBcel">https://www.igapyon.jp/blanco/blancodownload.html#blancoBcel</A>
</UL>
<P><FONT color="#ff00ff">ï¿½Ö˜Aï¿½ï¿½ï¿½ï¿½ï¿½ï¿½L</FONT></P>
<UL>
  <LI><A href="ig060110.html">2006/01/10 ï¿½ï¿½ï¿½L: Jassist ï¿½ï¿½pï¿½ï¿½ï¿½ï¿½ï¿½Nï¿½ï¿½ï¿½Xï¿½tï¿½@ï¿½Cï¿½ï¿½(ï¿½oï¿½Cï¿½gï¿½Rï¿½[ï¿½h)ï¿½ï¿½ÍƒTï¿½ï¿½ï¿½vï¿½ï¿½ , blancoJUnit2Docï¿½ï¿½ï¿½Ã“ï¿½ï¿½È–ï¿½ï¿½Ì‚Å‚ï¿½ï¿½é‚©ï¿½Ç‚ï¿½ï¿½ï¿½ï¿½ï¿½ï¿½ï¿½ï¿½ï¿½ï¿½ï¿½</A>
  <LI><A href="../2005/ig050719.html">2005/07/19 ï¿½ï¿½ï¿½L: Jakarta BCEL ï¿½ï¿½ï¿½p</A>
  <LI><A href="../2005/ig051130.html">2005/11/30 ï¿½ï¿½ï¿½L: blancoï¿½Pï¿½Ìï¿½ï¿½ï¿½ï¿½ï¿½ï¿½Ú•\ï¿½ï¿½ï¿½ï¿½ï¿½ï¿½ï¿½ï¿½(ï¿½ï¿½ï¿½ÌŒï¿½ï¿½ï¿½ï¿½ï¿½), blancoJUnitï¿½Íï¿½ï¿½ï¿½ï¿½ï¿½ï¿½ï¿½ï¿½ï¿½ï¿½ï¿½ï¿½ , ï¿½ï¿½ï¿½ï¿½NHKï¿½jï¿½ï¿½ï¿½[ï¿½Xï¿½É‚ÄÃ‰ï¿½ï¿½ÌƒKï¿½ï¿½ï¿½vï¿½ï¿½ï¿½Hï¿½ê‚ªï¿½ï¿½ï¿½f</A>
</UL>
<TABLE summary="mini title">
  <TBODY>
    <TR>
      <TD bgcolor="#ff9900" valign="top"><FONT color="#ffffff" size="+1"><STRONG>blancoDb EE 1.4.0, blancoResourceBundle 0.4.5, BlancoSqlEditorPlugin 0.3.4ï¿½oï¿½×Œï¿½ï¿½Åƒï¿½ï¿½ï¿½ï¿½[ï¿½X</STRONG></FONT></TD>
    </TR>
  </TBODY>
</TABLE>
<P><A HREF="https://www.igapyon.jp/blanco/blanco.ja.html" TITLE="blanco Framework ï¿½ï¿½ ï¿½Iï¿½[ï¿½vï¿½ï¿½ï¿½\ï¿½[ï¿½Xï¿½Å’ñ‹Ÿ‚ï¿½ï¿½ï¿½Ä‚ï¿½ï¿½ï¿½ blancoDbï¿½ï¿½blancoStrutsï¿½È‚Ç‚ÌWï¿½ï¿½ï¿½Ì‚Å‚ï¿½ï¿½Bï¿½ï¿½{ï¿½Iï¿½ï¿½ Javaï¿½\ï¿½[ï¿½Xï¿½Rï¿½[ï¿½hï¿½ï¿½ï¿½ï¿½ï¿½ï¿½ï¿½ï¿½ï¿½ï¿½ï¿½å‚½ï¿½ï¿½Ú“Iï¿½Æ‚ï¿½ï¿½Ü‚ï¿½ï¿½B">blanco</A> Framework ï¿½Ì\ï¿½ï¿½ï¿½vï¿½fï¿½Ì‚ï¿½ï¿½ï¿½ï¿½AblancoDb Enterprise Edition 1.4.0,
blancoResourceBundle 0.4.5, BlancoSqlEditorPlugin 0.3.4ï¿½É‚Â‚ï¿½ï¿½ÄAï¿½oï¿½×Œï¿½ï¿½Å‚ï¿½ï¿½ï¿½ï¿½ï¿½ï¿½[ï¿½Xï¿½ï¿½ï¿½Ü‚ï¿½ï¿½Bï¿½ï¿½ï¿½Ìˆï¿½Tï¿½Ô‚ÌŠÔ‚ï¿½
ï¿½oï¿½×Œï¿½ï¿½Å‚É‚ï¿½ï¿½ï¿½ï¿½Ä“ï¿½ï¿½É–ï¿½ï¿½ (ï¿½ï¿½ï¿½Éƒfï¿½Oï¿½ï¿½ï¿½[ï¿½hï¿½È‚ï¿½) ï¿½ï¿½ï¿½ï¿½ï¿½Â‚ï¿½ï¿½ï¿½È‚ï¿½ï¿½ï¿½ÎAï¿½ï¿½ï¿½ï¿½ï¿½ï¿½ÅVï¿½ï¿½ï¿½ï¿½Å‚ÆˆÊ’uï¿½Ã‚ï¿½ï¿½ï¿½\ï¿½ï¿½Å‚ï¿½ï¿½Bï¿½ï¿½ï¿½ÉŠÖŒWï¿½Ò‚Ì•ï¿½ï¿½Íƒ`ï¿½Fï¿½bï¿½Nï¿½ï¿½ï¿½ï¿½ï¿½è‚¢ï¿½ï¿½ï¿½ï¿½ï¿½ï¿½ï¿½Ü‚ï¿½ï¿½B<BR>
ï¿½È‚ï¿½ï¿½AblancoDbï¿½ï¿½ ï¿½dï¿½lï¿½ï¿½Ì•ÏXï¿½_ï¿½ï¿½ï¿½dï¿½vï¿½Å‚ï¿½ï¿½ï¿½Ælï¿½ï¿½ï¿½Aï¿½ï¿½ï¿½É‰ï¿½ï¿½Lï¿½Éƒï¿½ï¿½Xï¿½gï¿½Aï¿½bï¿½vï¿½ï¿½ï¿½Ü‚ï¿½ï¿½B</P>
<P><A HREF="https://www.igapyon.jp/blanco/blancodb.html" TITLE="ï¿½uSQLï¿½ï¿½`ï¿½ï¿½ï¿½vï¿½Æ‚ï¿½ï¿½ï¿½ Excelï¿½uï¿½bï¿½Nï¿½ï¿½ï¿½ï¿½Aï¿½fï¿½[ï¿½^ï¿½xï¿½[ï¿½Xï¿½ï¿½ï¿½oï¿½Í‚Ì‚ï¿½ï¿½ß‚Ìƒ\ï¿½[ï¿½Xï¿½Rï¿½[ï¿½hï¿½ï¿½ï¿½ï¿½ï¿½ï¿½ï¿½ï¿½ï¿½ï¿½ï¿½ï¿½ï¿½Ü‚ï¿½ï¿½B">blancoDb</A> Enterprise Edition ï¿½ï¿½ 1.2.0ï¿½ï¿½ï¿½ï¿½1.4.0ï¿½Ö‚Ìï¿½È•ÏXï¿½_ï¿½Í‰ï¿½ï¿½Lï¿½Ì‚æ‚¤ï¿½É‚È‚ï¿½Ü‚ï¿½ï¿½B</P>
<OL>
  <LI>Excelï¿½lï¿½ï¿½ï¿½ï¿½ï¿½ï¿½ï¿½Pï¿½ï¿½ï¿½Ü‚ï¿½ï¿½ï¿½ï¿½Bï¿½uSQLï¿½ï¿½`ï¿½ï¿½ï¿½vï¿½Ö‚Æ–ï¿½ï¿½Ì‚ï¿½ï¿½Ï‚ï¿½ï¿½Ü‚ï¿½ï¿½ï¿½ï¿½B
  <UL>
    <LI>Excelï¿½lï¿½ï¿½ï¿½ï¿½ï¿½uSQLï¿½ï¿½`ï¿½ï¿½ï¿½vï¿½Æ–ï¿½ï¿½Oï¿½ÏXï¿½ï¿½ï¿½Aï¿½ï¿½ï¿½eï¿½É‚Â‚ï¿½ï¿½Ä‚ï¿½ï¿½ï¿½ï¿½ï¿½ï¿½ï¿½ï¿½ï¿½ï¿½sï¿½ï¿½ï¿½Ü‚ï¿½ï¿½ï¿½ï¿½B
    <LI>ï¿½\ï¿½ï¿½ï¿½ó‚ ‚ï¿½Ü‚ï¿½ï¿½ñ‚ªAï¿½lï¿½ï¿½ï¿½É‚Â‚ï¿½ï¿½Ä‚ï¿½ 1.2.xï¿½n(ï¿½ï¿½ï¿½oï¿½[ï¿½Wï¿½ï¿½ï¿½ï¿½)ï¿½Ü‚Å‚Æ‚ÌŒİŠï¿½ï¿½ï¿½ï¿½Í‚ï¿½ï¿½ï¿½Ü‚ï¿½ï¿½ï¿½B
  </UL>
  <LI>ï¿½Xï¿½gï¿½Aï¿½hï¿½vï¿½ï¿½ï¿½Vï¿½[ï¿½Wï¿½ï¿½(CallableStatement)ï¿½Ö‚Ì‘Î‰ï¿½ï¿½ï¿½ï¿½sï¿½ï¿½ï¿½Ü‚ï¿½ï¿½ï¿½ï¿½B
  <UL>
    <LI>SQLï¿½ï¿½`ï¿½ï¿½ï¿½Åuï¿½Äoï¿½^ï¿½vï¿½ï¿½Iï¿½ï¿½ï¿½ï¿½ï¿½ï¿½ÆƒXï¿½gï¿½Aï¿½hï¿½vï¿½ï¿½ï¿½Vï¿½[ï¿½Wï¿½ï¿½ï¿½ï¿½ï¿½ï¿½ï¿½pï¿½Å‚ï¿½ï¿½Ü‚ï¿½ï¿½B
  </UL>
  <LI>ï¿½Pï¿½ï¿½\ï¿½Tï¿½|ï¿½[ï¿½gï¿½Ö˜A
  <UL>
    <LI>ï¿½Pï¿½ï¿½\ï¿½ï¿½SQLï¿½ï¿½ï¿½É‚Â‚ï¿½ï¿½Äƒ_ï¿½uï¿½ï¿½ï¿½Nï¿½Iï¿½[ï¿½gï¿½Gï¿½Xï¿½Pï¿½[ï¿½vï¿½ï¿½Kï¿½vï¿½Èê‡ï¿½É‚Ì‚İ•tï¿½^ï¿½ï¿½ï¿½ï¿½æ‚¤ï¿½É•ÏXï¿½ï¿½ï¿½Ü‚ï¿½ï¿½ï¿½ï¿½B<BR>
  ï¿½ï¿½ï¿½Ì‘Î‰ï¿½ï¿½É‚ï¿½ï¿½ MySQLï¿½Î‰ï¿½ï¿½ï¿½ï¿½Â”\ï¿½Æ‚È‚ï¿½Ü‚ï¿½ï¿½ï¿½ï¿½B<BR>
  ï¿½ï¿½ï¿½ï¿½ï¿½ HSQLDBï¿½Í‚ï¿½ï¿½Ì•ÏXï¿½É‚ï¿½è“®ï¿½ì‚µï¿½È‚ï¿½ï¿½È‚ï¿½Ü‚ï¿½ï¿½B<BR>
    ï¿½_ï¿½uï¿½ï¿½ï¿½Nï¿½Iï¿½[ï¿½gï¿½ï¿½ï¿½ï¿½ï¿½ï¿½ï¿½Æ“ï¿½ï¿½ì‚µï¿½È‚ï¿½ HSQLDBï¿½Ìdï¿½lï¿½ï¿½ï¿½ï¿½ï¿½ï¿½È‚ï¿½ï¿½Ì‚Å‚ï¿½ï¿½ï¿½Æ”ï¿½ï¿½fï¿½ï¿½ï¿½Ü‚ï¿½ï¿½B
    <LI>ï¿½Pï¿½ï¿½\ï¿½Aï¿½Nï¿½Zï¿½Xï¿½ÌƒXï¿½Nï¿½ï¿½ï¿½[ï¿½ï¿½ï¿½ï¿½ï¿½ï¿½ï¿½É‚Â‚ï¿½ï¿½ÄŒï¿½ï¿½ï¿½ï¿½ï¿½ï¿½ï¿½ï¿½ï¿½ï¿½{ï¿½ï¿½ï¿½Ü‚ï¿½ï¿½ï¿½ï¿½B<BR>
    ï¿½fï¿½tï¿½Hï¿½ï¿½ï¿½gï¿½ï¿½ï¿½Cï¿½ï¿½ï¿½Zï¿½ï¿½ï¿½Vï¿½eï¿½Bï¿½uï¿½Æ‚ï¿½ï¿½Ü‚ï¿½ï¿½B<BR>
    ï¿½vï¿½ï¿½ï¿½pï¿½eï¿½Bï¿½ÅƒXï¿½Nï¿½ï¿½ï¿½[ï¿½ï¿½ï¿½ï¿½ï¿½ï¿½ï¿½Í•ÏXï¿½ï¿½ï¿½Â”\ï¿½È‚æ‚¤ï¿½É‚ï¿½ï¿½Ü‚ï¿½ï¿½ï¿½ï¿½B
    <LI>ï¿½Pï¿½ï¿½\ï¿½Ì‘Sï¿½sSELECTï¿½É‚Â‚ï¿½ï¿½ÄA1.2ï¿½nï¿½Å‚Í–ï¿½ï¿½ï¿½ï¿½ï¿½ï¿½ï¿½ï¿½ï¿½Ä‚ï¿½ï¿½Ü‚ï¿½ï¿½ï¿½ï¿½ï¿½ï¿½Aï¿½ï¿½ï¿½ï¿½ğ•œŠï¿½ï¿½ï¿½ï¿½ï¿½ï¿½Ü‚ï¿½ï¿½ï¿½ï¿½B
    <LI>ï¿½ï¿½ï¿½oï¿½[ï¿½Wï¿½ï¿½ï¿½ï¿½ï¿½ÌŒİŠï¿½ï¿½ï¿½ï¿½Ì‚ï¿½ï¿½ß‚É“ï¿½ï¿½ï¿½ï¿½Iï¿½ÉƒTï¿½|ï¿½[ï¿½gï¿½ï¿½ï¿½Ä‚ï¿½ï¿½ï¿½ï¿½ï¿½ï¿½ï¿½ï¿½ï¿½TableGatewayï¿½Tï¿½|ï¿½[ï¿½gï¿½ï¿½ï¿½Iï¿½ï¿½ï¿½ï¿½ï¿½Ü‚ï¿½ï¿½ï¿½ï¿½B
    <LI>ï¿½Pï¿½ï¿½\ï¿½Ìƒeï¿½[ï¿½uï¿½ï¿½ï¿½É‚ï¿½ï¿½ï¿½ï¿½ï¿½ ï¿½\ï¿½ï¿½ï¿½ï¿½$ï¿½ï¿½ï¿½Ü‚Ü‚ï¿½Ä‚ï¿½ï¿½ï¿½ê‡ï¿½É‚ÍAï¿½ï¿½ï¿½ï¿½ï¿½ï¿½ï¿½ï¿½ï¿½È‚ï¿½ï¿½æ‚¤ï¿½Édï¿½lï¿½ÏXï¿½ï¿½ï¿½Ü‚ï¿½ï¿½ï¿½ï¿½B<BR>
    ï¿½ï¿½ï¿½ï¿½ï¿½ Oracle10gï¿½É‚ï¿½ï¿½ï¿½ï¿½ÄAï¿½íœï¿½eï¿½[ï¿½uï¿½ï¿½ï¿½È‚Ç‚ï¿½ BIN$ï¿½ï¿½ï¿½ï¿½ï¿½Æ‚ï¿½ï¿½ï¿½ï¿½eï¿½[ï¿½uï¿½ï¿½ï¿½Æ‚ï¿½ï¿½ÄŠiï¿½[ï¿½ï¿½ï¿½ï¿½ï¿½dï¿½lï¿½Ö‚Ì‘Î‰ï¿½ï¿½Ì‚ï¿½ï¿½ß‚Å‚ï¿½ï¿½B
  </UL>
  <LI>ï¿½ï¿½ï¿½Mï¿½ï¿½ï¿½Oï¿½Ö‚Ì‘Î‰ï¿½
  <UL>
    <LI>Jakarta Commons Loggingï¿½É‘Î‰ï¿½ï¿½ï¿½ï¿½Ü‚ï¿½ï¿½ï¿½ï¿½B
  </UL>
  <LI>ï¿½Vï¿½ï¿½ï¿½Èƒfï¿½[ï¿½^ï¿½xï¿½[ï¿½Xï¿½Ö‚Ì‘Î‰ï¿½
  <UL>
    <LI>Oracle10gï¿½Å“ï¿½ï¿½ï¿½mï¿½Fï¿½ï¿½ï¿½Ü‚ï¿½ï¿½ï¿½ï¿½B<BR>
    ï¿½ï¿½ï¿½ï¿½ï¿½Ü‚Ü‚Å‚ï¿½ Oracle 9iï¿½Ü‚Å‚Ì‘Î‰ï¿½ï¿½Å‚ï¿½ï¿½ï¿½ï¿½B
    <LI>MySQLï¿½ÅŠÈ’Pï¿½È“ï¿½ï¿½ï¿½mï¿½Fï¿½ï¿½ï¿½ï¿½ï¿½Ü‚ï¿½ï¿½ï¿½ï¿½B
  </UL>
  <LI>ï¿½Gï¿½ï¿½ï¿½[ï¿½ï¿½ï¿½Ìï¿½ï¿½ï¿½
  <UL>
    <LI>ï¿½ï¿½ÈƒGï¿½ï¿½ï¿½[ï¿½ï¿½ï¿½bï¿½Zï¿½[ï¿½Wï¿½ï¿½ï¿½ï¿½ï¿½\ï¿½[ï¿½Xï¿½oï¿½ï¿½ï¿½hï¿½ï¿½ï¿½ï¿½ï¿½ï¿½ï¿½Ü‚ï¿½ï¿½ï¿½ï¿½B
    <LI>ï¿½oï¿½Cï¿½ï¿½ï¿½hï¿½Yï¿½ï¿½Ìƒpï¿½ï¿½ï¿½ï¿½ï¿½[ï¿½^ï¿½ï¿½ï¿½ï¿½ï¿½ï¿½ê‡ï¿½É—ï¿½Oï¿½ï¿½ï¿½ï¿½ï¿½ï¿½ï¿½ï¿½ï¿½ï¿½æ‚¤ï¿½É•ÏXï¿½ï¿½ï¿½Ü‚ï¿½ï¿½ï¿½ï¿½B<BR>
    ï¿½Ü‚ï¿½ï¿½ASQLï¿½ï¿½Oï¿½ï¿½ ï¿½È‚ï¿½×‚ï¿½ï¿½ï¿½ï¿½Ì‚Ü‚Ü“`ï¿½ï¿½ï¿½æ‚¤ï¿½É‰ï¿½ï¿½Pï¿½ï¿½ï¿½Aï¿½ï¿½ï¿½ï¿½ï¿½ï¿½ï¿½ï¿½ï¿½ï¿½ï¿½ï¿½ï¿½â‚·ï¿½ï¿½ï¿½æ‚¤ï¿½É‚ï¿½ï¿½Ü‚ï¿½ï¿½ï¿½ï¿½B
  </UL>
  <LI>ï¿½ï¿½ï¿½ï¿½ï¿½ï¿½ï¿½ï¿½ï¿½Ì‰ï¿½ï¿½P
  <UL>
    <LI>ï¿½ï¿½ï¿½Oï¿½ÏŒ`ï¿½Ìï¿½ï¿½ï¿½ï¿½ğ”²–{ï¿½Iï¿½ÉŒï¿½ï¿½ï¿½ï¿½ï¿½ï¿½Ü‚ï¿½ï¿½ï¿½ï¿½B
    <LI>ï¿½vï¿½ï¿½ï¿½Oï¿½Cï¿½ï¿½ï¿½Ìiï¿½ï¿½ï¿½oï¿½[ï¿½Ì•\ï¿½ï¿½ï¿½ï¿½ï¿½sï¿½Kï¿½Ø‚Å‚ï¿½ï¿½ï¿½ï¿½ï¿½ï¿½Ì‚ï¿½ï¿½Cï¿½ï¿½ï¿½ï¿½ï¿½Ü‚ï¿½ï¿½ï¿½ï¿½B
    <LI>ï¿½vï¿½ï¿½ï¿½Oï¿½Cï¿½ï¿½ï¿½ï¿½Exception, Errorï¿½ï¿½Eclipseï¿½Ìƒï¿½ï¿½Oï¿½É“Kï¿½Ø‚Éoï¿½Í‚ï¿½ï¿½ï¿½ï¿½æ‚¤ï¿½É‰ï¿½ï¿½Pï¿½B
    <LI>ï¿½ï¿½ï¿½Ì‘ï¿½ï¿½Aï¿½\ï¿½[ï¿½Xï¿½Rï¿½[ï¿½hï¿½Ì‘å•ï¿½Èï¿½ï¿½ï¿½ï¿½ï¿½ï¿½ï¿½ï¿½{ï¿½ï¿½ï¿½Ü‚ï¿½ï¿½ï¿½ï¿½Bï¿½ï¿½ï¿½Xï¿½eï¿½bï¿½vï¿½ï¿½ï¿½ï¿½ï¿½ï¿½ï¿½È‚èŒ¸ï¿½ï¿½Ü‚ï¿½ï¿½ï¿½ï¿½B
  </UL>
</OL>
<HR>
<address><A HREF="../memo/memoigapyon.html">ï¿½ï¿½ï¿½ï¿½ï¿½Ò‚ï¿½ï¿½É‚Â‚ï¿½ï¿½ï¿½</A><BR>
Last modified: $Date: 2010/09/27 20:42:49 $</address>
</BODY>
</HTML>
